[{"message":"scheduling build on Metal builder \"builder-pojtuv\"","timestamp":"2026-02-09T06:09:55.909986738Z"},{"message":"scheduling build on Metal builder \"builder-pojtuv\"","timestamp":"2026-02-09T06:10:07.396097297Z"},{"message":"[snapshot] received sha256:105dfba84a4fc448845686ea66748505e18fc6bd715cc0179f7148053aa2270d md5:308320e8cac8c8756c1f9f5d9beb91fa","timestamp":"2026-02-09T06:10:26.621175143Z"},{"message":"receiving snapshot","timestamp":"2026-02-09T06:10:26.621292503Z"},{"message":"root directory set as 'backend'","timestamp":"2026-02-09T06:10:27.402961590Z"},{"message":"found 'Dockerfile' at 'backend/Dockerfile'","timestamp":"2026-02-09T06:10:27.402970841Z"},{"message":"skipping 'Dockerfile' at 'frontend/Dockerfile' as it is not rooted at a valid path (root_dir=backend, fileOpts={acceptChildOfRepoRoot:false})","timestamp":"2026-02-09T06:10:27.402976470Z"},{"message":"root directory sanitized to 'backend'","timestamp":"2026-02-09T06:10:27.402977610Z"},{"message":"analyzing snapshot","timestamp":"2026-02-09T06:10:27.403096010Z"},{"message":"uploading snapshot","timestamp":"2026-02-09T06:10:28.751092166Z"},{"message":"fetched snapshot sha256:105dfba84a4fc448845686ea66748505e18fc6bd715cc0179f7148053aa2270d (41 MB bytes)","timestamp":"2026-02-09T06:10:32.937329466Z"},{"message":"fetching snapshot","timestamp":"2026-02-09T06:10:32.937354256Z"},{"message":"unpacking archive","timestamp":"2026-02-09T06:10:34.516963215Z"},{"message":"[internal] load build definition from backend/Dockerfile","timestamp":"2026-02-09T06:10:34.967795001Z"},{"message":"[internal] load build definition from backend/Dockerfile","timestamp":"2026-02-09T06:10:34.967828911Z"},{"message":"[internal] load build definition from backend/Dockerfile","timestamp":"2026-02-09T06:10:34.967935211Z"},{"message":"[internal] load build definition from backend/Dockerfile","timestamp":"2026-02-09T06:10:35.079426969Z"},{"message":"[internal] load metadata for ghcr.io/astral-sh/uv:latest","timestamp":"2026-02-09T06:10:35.094901143Z"},{"message":"[internal] load metadata for docker.io/library/python:3.12-slim","timestamp":"2026-02-09T06:10:35.094906803Z"},{"message":"[internal] load metadata for docker.io/library/python:3.12-slim","timestamp":"2026-02-09T06:10:35.249028448Z"},{"message":"[internal] load metadata for ghcr.io/astral-sh/uv:latest","timestamp":"2026-02-09T06:10:35.516041143Z"},{"message":"[internal] load .dockerignore","timestamp":"2026-02-09T06:10:35.516657124Z"},{"message":"[internal] load .dockerignore","timestamp":"2026-02-09T06:10:35.516771134Z"},{"message":"[internal] load .dockerignore","timestamp":"2026-02-09T06:10:35.516866264Z"},{"message":"[internal] load .dockerignore","timestamp":"2026-02-09T06:10:35.602813979Z"},{"message":"[stage-0 8/8] COPY --chown=appuser:appuser . .","timestamp":"2026-02-09T06:10:35.640077392Z"},{"message":"[stage-0 7/8] RUN uv pip install --system --no-cache -r requirements.txt","timestamp":"2026-02-09T06:10:35.640081982Z"},{"message":"[stage-0 6/8] COPY requirements.txt .","timestamp":"2026-02-09T06:10:35.640082622Z"},{"message":"[internal] load build context","timestamp":"2026-02-09T06:10:35.640082862Z"},{"message":"[stage-0 5/8] COPY --from=ghcr.io/astral-sh/uv:latest /uv /usr/local/bin/uv","timestamp":"2026-02-09T06:10:35.640083002Z"},{"message":"FROM ghcr.io/astral-sh/uv:latest@sha256:78a7ff97cd27b7124a5f3c2aefe146170793c56a1e03321dd31a289f6d82a04f","timestamp":"2026-02-09T06:10:35.640083272Z"},{"message":"[stage-0 4/8] RUN groupadd -r appuser && useradd -r -g appuser appuser &&     chown -R appuser:appuser /app","timestamp":"2026-02-09T06:10:35.640083432Z"},{"message":"[stage-0 3/8] RUN apt-get update && apt-get install -y     build-essential     libpq-dev     && rm -rf /var/lib/apt/lists/*","timestamp":"2026-02-09T06:10:35.640083562Z"},{"message":"[stage-0 2/8] WORKDIR /app","timestamp":"2026-02-09T06:10:35.640083712Z"},{"message":"[stage-0 1/8] FROM docker.io/library/python:3.12-slim@sha256:9e01bf1ae5db7649a236da7be1e94ffbbbdd7a93f867dd0d8d5720d9e1f89fab","timestamp":"2026-02-09T06:10:35.640083872Z"},{"message":"[stage-0 1/8] FROM docker.io/library/python:3.12-slim@sha256:9e01bf1ae5db7649a236da7be1e94ffbbbdd7a93f867dd0d8d5720d9e1f89fab","timestamp":"2026-02-09T06:10:35.640223292Z"},{"message":"FROM ghcr.io/astral-sh/uv:latest@sha256:78a7ff97cd27b7124a5f3c2aefe146170793c56a1e03321dd31a289f6d82a04f","timestamp":"2026-02-09T06:10:35.640225432Z"},{"message":"[internal] load build context","timestamp":"2026-02-09T06:10:35.640230272Z"},{"message":"[internal] load build context","timestamp":"2026-02-09T06:10:35.640527252Z"},{"message":"[stage-0 1/8] FROM docker.io/library/python:3.12-slim@sha256:9e01bf1ae5db7649a236da7be1e94ffbbbdd7a93f867dd0d8d5720d9e1f89fab","timestamp":"2026-02-09T06:10:35.679865817Z"},{"message":"[stage-0 1/8] FROM docker.io/library/python:3.12-slim@sha256:9e01bf1ae5db7649a236da7be1e94ffbbbdd7a93f867dd0d8d5720d9e1f89fab","timestamp":"2026-02-09T06:10:35.680251658Z"},{"message":"[stage-0 1/8] FROM docker.io/library/python:3.12-slim@sha256:9e01bf1ae5db7649a236da7be1e94ffbbbdd7a93f867dd0d8d5720d9e1f89fab","timestamp":"2026-02-09T06:10:35.680259847Z"},{"message":"FROM ghcr.io/astral-sh/uv:latest@sha256:78a7ff97cd27b7124a5f3c2aefe146170793c56a1e03321dd31a289f6d82a04f","timestamp":"2026-02-09T06:10:35.682769460Z"},{"message":"[internal] load build context","timestamp":"2026-02-09T06:10:35.800261243Z"},{"message":"[stage-0 2/8] WORKDIR /app","timestamp":"2026-02-09T06:10:35.823201513Z"},{"message":"[stage-0 3/8] RUN apt-get update && apt-get install -y     build-essential     libpq-dev     && rm -rf /var/lib/apt/lists/*","timestamp":"2026-02-09T06:10:35.823205393Z"},{"message":"[stage-0 4/8] RUN groupadd -r appuser && useradd -r -g appuser appuser &&     chown -R appuser:appuser /app","timestamp":"2026-02-09T06:10:35.823206663Z"},{"message":"[stage-0 5/8] COPY --from=ghcr.io/astral-sh/uv:latest /uv /usr/local/bin/uv","timestamp":"2026-02-09T06:10:35.823206893Z"},{"message":"[stage-0 6/8] COPY requirements.txt .","timestamp":"2026-02-09T06:10:35.823207033Z"},{"message":"[stage-0 7/8] RUN uv pip install --system --no-cache -r requirements.txt","timestamp":"2026-02-09T06:10:35.823207163Z"},{"message":"[stage-0 8/8] COPY --chown=appuser:appuser . .","timestamp":"2026-02-09T06:10:35.823209283Z"},{"message":"[stage-0 8/8] COPY --chown=appuser:appuser . .","timestamp":"2026-02-09T06:10:36.903280773Z"},{"message":"exporting to docker image format","timestamp":"2026-02-09T06:10:36.925076252Z"},{"message":"exporting to docker image format","timestamp":"2026-02-09T06:10:38.283403166Z"},{"message":"containerimage.digest: sha256:bf6df919d0fd7e7ada4a3cefe540c997dc4d139a41681da95a4e19aabc1b31e6","timestamp":"2026-02-09T06:10:38.332329849Z"},{"message":"containerimage.descriptor: eyJtZWRpYVR5cGUiOiJhcHBsaWNhdGlvbi92bmQub2NpLmltYWdlLm1hbmlmZXN0LnYxK2pzb24iLCJkaWdlc3QiOiJzaGEyNTY6YmY2ZGY5MTlkMGZkN2U3YWRhNGEzY2VmZTU0MGM5OTdkYzRkMTM5YTQxNjgxZGE5NWE0ZTE5YWFiYzFiMzFlNiIsInNpemUiOjIzOTMsImFubm90YXRpb25zIjp7Im9yZy5vcGVuY29udGFpbmVycy5pbWFnZS5jcmVhdGVkIjoiMjAyNi0wMi0wOVQwNjoxMDozN1oifSwicGxhdGZvcm0iOnsiYXJjaGl0ZWN0dXJlIjoiYW1kNjQiLCJvcyI6ImxpbnV4In19","timestamp":"2026-02-09T06:10:38.332335649Z"},{"message":"containerimage.config.digest: sha256:3fec909b59eca0f574d883a46df8443de812f87f6ec9baeee4f715b459e9d284","timestamp":"2026-02-09T06:10:38.332337319Z"},{"message":"","timestamp":"2026-02-09T06:10:38.376685968Z"},{"message":"\u001b[35m====================\nStarting Healthcheck\n====================\n\u001b[0m","timestamp":"2026-02-09T06:10:38.376741312Z"},{"message":"\u001b[37mPath: /api/health\u001b[0m","timestamp":"2026-02-09T06:10:38.376743656Z"},{"message":"\u001b[37mRetry window: 5m0s\u001b[0m","timestamp":"2026-02-09T06:10:38.376746435Z"},{"message":"","timestamp":"2026-02-09T06:10:38.376747491Z"},{"message":"\u001b[93mAttempt #1 failed with service unavailable. Continuing to retry for 4m55s\u001b[0m","timestamp":"2026-02-09T06:10:42.518367551Z"},{"message":"\u001b[93mAttempt #2 failed with service unavailable. Continuing to retry for 4m54s\u001b[0m","timestamp":"2026-02-09T06:10:43.548226667Z"},{"message":"\u001b[93mAttempt #3 failed with service unavailable. Continuing to retry for 4m52s\u001b[0m","timestamp":"2026-02-09T06:10:45.579892937Z"},{"message":"\u001b[93mAttempt #4 failed with service unavailable. Continuing to retry for 4m48s\u001b[0m","timestamp":"2026-02-09T06:10:49.610063818Z"},{"message":"image push","timestamp":"2026-02-09T06:10:50.581137008Z"},{"message":"\u001b[93mAttempt #5 failed with service unavailable. Continuing to retry for 4m40s\u001b[0m","timestamp":"2026-02-09T06:10:57.640112814Z"},{"message":"\u001b[93mAttempt #6 failed with service unavailable. Continuing to retry for 4m24s\u001b[0m","timestamp":"2026-02-09T06:11:13.673575177Z"}]